scheduler/__init__.py
scheduler/__main__.py
scheduler/config.py
scheduler/core_api.py
scheduler/decorators.py
scheduler/filters.py
scheduler/log.py
scheduler/router.py
scheduler/static/css/input.css
scheduler/static/css/tailwind.css
scheduler/static/js/htmx.min.js
scheduler/static/js/main.js
scheduler/templates/index.html
scheduler/templates/job_details_partial.html
scheduler/templates/jobs_partial.html
taranis_scheduler-0.3.3.dist-info/LICENSE.md
taranis_scheduler-0.3.3.dist-info/METADATA
taranis_scheduler-0.3.3.dist-info/WHEEL
taranis_scheduler-0.3.3.dist-info/top_level.txt
taranis_scheduler-0.3.3.dist-info/RECORD
