Metadata-Version: 2.1
Name: taranis-scheduler
Version: 0.3.3
Summary: Taranis AI Scheduler
Maintainer-email: AIT <benjamin.akhras@ait.ac.at>
License: EUROPEAN UNION PUBLIC LICENCE v. 1.2
Project-URL: Source Code, https://github.com/taranis-ai/taranis-scheduler
Classifier: Programming Language :: Python
Classifier: Programming Language :: Python :: 3
Classifier: Programming Language :: Python :: 3.12
Classifier: Framework :: Flask
Classifier: Topic :: Security
Requires-Python: >=3.12
License-File: LICENSE.md
Requires-Dist: Flask
Requires-Dist: flask-htmx
Requires-Dist: flask-cors
Requires-Dist: click
Requires-Dist: pydantic-settings
Requires-Dist: python-dotenv
Requires-Dist: granian
Requires-Dist: requests
Requires-Dist: setuptools
Provides-Extra: dev
Requires-Dist: ruff; extra == "dev"
Requires-Dist: pytest; extra == "dev"
Requires-Dist: pytest-flask; extra == "dev"
Requires-Dist: build; extra == "dev"
Requires-Dist: wheel; extra == "dev"
Requires-Dist: setuptools-scm; extra == "dev"
Requires-Dist: requests-mock; extra == "dev"
